parcha_api/__init__.py
parcha_api/api.py
parcha_api/models.py
parcha_api-0.1.1.dist-info/METADATA
parcha_api-0.1.1.dist-info/WHEEL
parcha_api-0.1.1.dist-info/RECORD
