Metadata-Version: 2.1
Name: parcha-api
Version: 0.1.1
Summary: Python client for interacting with the Parcha API, providing both synchronous and asynchronous methods for various API endpoints.
Home-page: https://docs.parcha.ai
License: Proprietary
Keywords: KYB,KYC,API client,Parcha,business verification,customer verification,compliance
Author: Miguel Rios
Author-email: miguel@parcha.ai
Requires-Python: >=3.8,<4.0
Classifier: Development Status :: 4 - Beta
Classifier: Intended Audience :: Developers
Classifier: Intended Audience :: Financial and Insurance Industry
Classifier: License :: Other/Proprietary License
Classifier: Programming Language :: Python :: 3
Classifier: Programming Language :: Python :: 3.8
Classifier: Programming Language :: Python :: 3.9
Classifier: Programming Language :: Python :: 3.10
Classifier: Programming Language :: Python :: 3.11
Classifier: Programming Language :: Python :: 3.12
Classifier: Programming Language :: Python :: 3.7
Classifier: Topic :: Office/Business :: Financial
Classifier: Topic :: Office/Business :: Financial :: Investment
Classifier: Topic :: Scientific/Engineering :: Artificial Intelligence
Classifier: Topic :: Security
Classifier: Topic :: Software Development :: Libraries :: Application Frameworks
Classifier: Topic :: Software Development :: Libraries :: Python Modules
Provides-Extra: test
Requires-Dist: aiohttp (>=3.10.5,<4.0.0)
Requires-Dist: pydantic (>=2.9.0,<3.0.0)
Requires-Dist: requests (>=2.32.3,<3.0.0)
Project-URL: Documentation, https://docs.parcha.ai
Project-URL: Repository, https://github.com/parcha-ai/parcha-api-python
